{
  "N": {
    "a": {
      "t": 5
    },
    "b": {
      "t": 5
    },
    "c": {
      "t": 5
    },
    "d": {
      "t": 6
    },
    "e": {
      "t": 6
    },
    "f": {
      "t": 6
    },
    "g": {
      "t": 7
    },
    "h": {
      "t": 7
    },
    "i": {
      "t": 7
    },
    "j": {
      "t": 8
    },
    "k": {
      "t": 8
    },
    "l": {
      "t": 8
    }
  },
  "EN": {},
  "ET": {
    "0": {
      "a": [
        "e"
      ],
      "b": [
        "d"
      ],
      "c": [
        "d"
      ]
    },
    "1": {
      "d": [
        "g"
      ],
      "e": [
        "g",
        "h",
        "i"
      ],
      "f": [
        "h"
      ]
    },
    "2": {
      "g": [
        "l"
      ],
      "h": [
        "j",
        "k"
      ]
    }
  }
}